{
  "fuente": "Infaoliva",
  "fecha": "2025-10-25 11:13:34",
  "precios": {
    "Aceite de oliva virgen extra": {
      "variedad": "Picual",
      "precio_eur_kg": 4.108
    },
    "Aceite de oliva virgen": {
      "variedad": "Picual",
      "precio_eur_kg": 3.65
    },
    "Aceite de oliva lampante": {
      "variedad": "Picual",
      "precio_eur_kg": 3.488
    }
  },
  "ultima_actualizacion": "2025-10-25T11:13:34.904048",
  "generated_at": "2025-10-25T11:13:34.904048",
  "sin_cierre_operaciones": false
}