{
  "fuente": "Infaoliva",
  "fecha": "2025-09-15 09:57:19",
  "precios": {
    "Aceite de oliva virgen extra": {
      "variedad": "Picual",
      "precio_eur_kg": 4.0
    },
    "Aceite de oliva virgen": {
      "variedad": "Picual",
      "precio_eur_kg": 3.59
    },
    "Aceite de oliva lampante": {
      "variedad": "Picual",
      "precio_eur_kg": 3.45
    }
  },
  "ultima_actualizacion": "2025-09-15T09:57:19.664657",
  "generated_at": "2025-09-15T09:57:19.664657",
  "sin_cierre_operaciones": false
}